TDPU/vec_multi_core.sv
`timescale 1ns / 1ps
`include "package_def.sv"
import package_def::*;
// ============================================================
// vec_multi_core.sv
// 多核向量乘加计算单元 (Vector Multiply-Accumulate Core)
// 支持参数化向量长度和数据位宽
// 较先前版本做了以下改进：
// 1. 整体采用动态位宽，在最后输出才进行位宽固定为32位
// 2. 控制路径复位，数据路径无复位，极大地降低了全局复位信号的扇出，缓解了布线拥塞
// 3. 加法树第0层输入直连 PE 输出，减少寄存器级数，降低延迟
// 4. 消除always块内的if else语句Bug,比如level 0和level>0
// ============================================================
module vec_multi_core #(
    parameter int LEN = 32,
    // Parameter LEN must be power of 2 (e.g., 32, 64)
    parameter int DATA_WIDTH = 8
) (
    input logic clk,
    input logic rst_n,
    input logic i_data_valid,
    input logic i_load_weight,
    input logic signed [LEN-1:0][DATA_WIDTH-1:0] i_data,
    input weight_t [LEN-1:0] i_weight,
    output logic o_data_ready,
    output logic signed [31:0] o_result
);

  // ============================================================
  // 0. 权重寄存器
  // ============================================================
  weight_t [LEN-1:0] weight_reg;
  always_ff @(posedge clk or negedge rst_n) begin : blk_weight
    if (!rst_n) begin
      weight_reg <= '{default: W_ZERO};
    end else if (i_load_weight) begin
      weight_reg <= i_weight;
    end
  end

  // ============================================================
  // 1. PE计算层 (BitLinear Core)
  // ============================================================
  // 优化：DATA_WIDTH(8) -> PROD_WIDTH(9)
  localparam int PROD_WIDTH = DATA_WIDTH + 1;
  logic signed [LEN-1:0][PROD_WIDTH-1:0] product;
  logic product_ready;

  generate
    for (genvar i = 0; i < LEN; i++) begin : gen_PE
      // 数据通路去复位，只保留 Enable
      always_ff @(posedge clk) begin
        if (i_data_valid) begin
          unique case (weight_reg[i])
            W_POS:   product[i] <= PROD_WIDTH'(i_data[i]);
            W_NEG:   product[i] <= -PROD_WIDTH'(i_data[i]);
            W_ZERO:  product[i] <= 'sb0;
            default: product[i] <= 'sb0;
          endcase
        end
      end
    end
  endgenerate

  // 控制信号复位
  always_ff @(posedge clk or negedge rst_n) begin
    if (!rst_n) product_ready <= 1'b0;
    else product_ready <= i_data_valid;
  end

  // ============================================================
  // 2. 参数化加法树 (Adder Tree) - 修复版
  // ============================================================
  localparam int TREE_DEPTH = $clog2(LEN);
  logic [TREE_DEPTH-1:0] tree_valid;

  generate
    for (genvar level = 0; level < TREE_DEPTH; level++) begin : gen_tree

      // 计算当前层的位宽和节点数
      localparam int OUT_WIDTH = PROD_WIDTH + level + 1;
      localparam int NUM_NODES = LEN >> (level + 1);

      // 定义当前层的数据寄存器
      logic signed [NUM_NODES-1:0][OUT_WIDTH-1:0] level_data;

      // ==========================================================
      // [修复重点] 使用 if - else 结构，去掉 redundant 的 else if
      // ==========================================================
      if (level == 0) begin : g_level_zero
        // ------------------------------------------------
        // Case A: 第一层 (Level 0)，输入直接来自 product
        // ------------------------------------------------
        for (genvar k = 0; k < NUM_NODES; k++) begin : gen_loop_l0
          always_ff @(posedge clk) begin
            if (product_ready) begin
              // 9bit + 9bit -> 10bit
              level_data[k] <= product[2*k] + product[2*k+1];
            end
          end
        end

      end else begin : g_level_upper
        // ------------------------------------------------
        // Case B: 后续层 (Level >= 1)，输入来自上一级
        // 此时 level-1 绝对安全，不会越界
        // ------------------------------------------------
        for (genvar k = 0; k < NUM_NODES; k++) begin : gen_loop_lx
          always_ff @(posedge clk) begin
            // 引用上一层 gen_tree[level-1]
            if (tree_valid[level-1]) begin
              level_data[k] <= gen_tree[level-1].level_data[2*k] + 
                                   gen_tree[level-1].level_data[2*k+1];
            end
          end
        end
      end
      // ==========================================================

      // Valid 信号流水线
      //如果leverl不分开0级处理，会导致综合工具报错（level-1在0级时会出现负数）
      //if-else内包always不会报错，always内包if-else会报错
      if (level == 0) begin : g_valid_0
        always_ff @(posedge clk or negedge rst_n) begin
          if (!rst_n) begin
            tree_valid[level] <= 1'b0;
          end else begin
            tree_valid[level] <= product_ready;
          end
        end
      end else begin : g_valid_upper
        always_ff @(posedge clk or negedge rst_n) begin
          if (!rst_n) begin
            tree_valid[level] <= 1'b0;
          end else begin
            tree_valid[level] <= tree_valid[level-1];
          end
        end
      end

    end
  endgenerate

  // ============================================================
  // 3. 输出处理
  // ============================================================
  // 符号扩展到 32 位
  assign o_result     = 32'(gen_tree[TREE_DEPTH-1].level_data[0]);
  assign o_data_ready = tree_valid[TREE_DEPTH-1];

endmodule

TDPU/waveform.vcd
$version Generated by VerilatedVcd $end
$timescale 1ps $end
 $scope module TOP $end
  $var wire 1 8 clk $end
  $var wire 1 9 rst_n $end
  $var wire 1 : i_data_valid $end
  $var wire 1 ; i_load_weight $end
  $var wire 256 < i_data [255:0] $end
  $var wire 64 D i_weight [63:0] $end
  $var wire 1 F o_data_ready $end
  $var wire 32 G o_result [31:0] $end
  $scope module vec_multi_core $end
   $var wire 32 L LEN [31:0] $end
   $var wire 32 M DATA_WIDTH [31:0] $end
   $var wire 1 8 clk $end
   $var wire 1 9 rst_n $end
   $var wire 1 : i_data_valid $end
   $var wire 1 ; i_load_weight $end
   $var wire 256 < i_data [255:0] $end
   $var wire 64 D i_weight [63:0] $end
   $var wire 1 F o_data_ready $end
   $var wire 32 G o_result [31:0] $end
   $var wire 64 H weight_reg [63:0] $end
   $var wire 32 N PROD_WIDTH [31:0] $end
   $var wire 288 # product [287:0] $end
   $var wire 1 J product_ready $end
   $var wire 32 O TREE_DEPTH [31:0] $end
   $var wire 5 K tree_valid [4:0] $end
   $scope module gen_tree[0] $end
    $var wire 32 P OUT_WIDTH [31:0] $end
    $var wire 32 Q NUM_NODES [31:0] $end
    $var wire 160 , level_data [159:0] $end
   $upscope $end
   $scope module gen_tree[1] $end
    $var wire 32 R OUT_WIDTH [31:0] $end
    $var wire 32 M NUM_NODES [31:0] $end
    $var wire 88 1 level_data [87:0] $end
   $upscope $end
   $scope module gen_tree[2] $end
    $var wire 32 S OUT_WIDTH [31:0] $end
    $var wire 32 T NUM_NODES [31:0] $end
    $var wire 48 4 level_data [47:0] $end
   $upscope $end
   $scope module gen_tree[3] $end
    $var wire 32 U OUT_WIDTH [31:0] $end
    $var wire 32 V NUM_NODES [31:0] $end
    $var wire 26 6 level_data [25:0] $end
   $upscope $end
   $scope module gen_tree[4] $end
    $var wire 32 W OUT_WIDTH [31:0] $end
    $var wire 32 X NUM_NODES [31:0] $end
    $var wire 14 7 level_data [13:0] $end
   $upscope $end
  $upscope $end
 $upscope $end
$enddefinitions $end


#0
b000000000000000000000000000000000000000000000000000000000000000000000000000000000000000000000000000000000000000000000000000000000000000000000000000000000000000000000000000000000000000000000000000000000000000000000000000000000000000000000000000000000000000000000000000000000000000000000000 #
b0000000000000000000000000000000000000000000000000000000000000000000000000000000000000000000000000000000000000000000000000000000000000000000000000000000000000000 ,
b0000000000000000000000000000000000000000000000000000000000000000000000000000000000000000 1
b000000000000000000000000000000000000000000000000 4
b00000000000000000000000000 6
b00000000000000 7
18
09
0:
0;
b0000000000000000000000000000000000000000000000000000000000000000000000000000000000000000000000000000000000000000000000000000000000000000000000000000000000000000000000000000000000000000000000000000000000000000000000000000000000000000000000000000000000000000 <
b0101010101010101010101010101010101010101010101010101010101010101 D
0F
b00000000000000000000000000000000 G
b0000000000000000000000000000000000000000000000000000000000000000 H
0J
b00000 K
b00000000000000000000000000100000 L
b00000000000000000000000000001000 M
b00000000000000000000000000001001 N
b00000000000000000000000000000101 O
b00000000000000000000000000001010 P
b00000000000000000000000000010000 Q
b00000000000000000000000000001011 R
b00000000000000000000000000001100 S
b00000000000000000000000000000100 T
b00000000000000000000000000001101 U
b00000000000000000000000000000010 V
b00000000000000000000000000001110 W
b00000000000000000000000000000001 X
#1
08
#2
18
b0101010101010101010101010101010101010101010101010101010101010101 H
#3
08
#4
18
#5
08
#6
18
#7
08
#8
18
#9
08
#10
18
#11
08
#12
18
#13
08
#14
18
#15
08
#16
18
#17
08
#18
18
#19
08
#20
18
19
#21
08
#22
18
1;
b1010101010101010101010101010101010101010101010101010101010101010 D
b1010101010101010101010101010101010101010101010101010101010101010 H
#23
08
#24
b000001010000001010000001010000001010000001010000001010000001010000001010000001010000001010000001010000001010000001010000001010000001010000001010000001010000001010000001010000001010000001010000001010000001010000001010000001010000001010000001010000001010000001010000001010000001010000001010 #
18
1:
0;
b0000101000001010000010100000101000001010000010100000101000001010000010100000101000001010000010100000101000001010000010100000101000001010000010100000101000001010000010100000101000001010000010100000101000001010000010100000101000001010000010100000101000001010 <
1J
#25
08
#26
b0000010100000001010000000101000000010100000001010000000101000000010100000001010000000101000000010100000001010000000101000000010100000001010000000101000000010100 ,
18
0:
0J
b00001 K
#27
08
#28
b0000010100000000101000000001010000000010100000000101000000001010000000010100000000101000 1
18
b00010 K
#29
08
#30
b000001010000000001010000000001010000000001010000 4
18
b00100 K
#31
08
#32
b00000101000000000010100000 6
18
b01000 K
#33
08
#34
b00000101000000 7
18
1F
b00000000000000000000000101000000 G
b10000 K
#35
08
#36
18
0F
b00000 K
#37
08
#38
18
#39
08
#40
18
#41
08
#42
18
#43
08
#44
18
#45
08
#46
18
1;
b0000000000000000000000000000000000000000000000000000000000000000 D
b0000000000000000000000000000000000000000000000000000000000000000 H
#47
08
#48
b111111011111111011111111011111111011111111011111111011111111011111111011111111011111111011111111011111111011111111011111111011111111011111111011111111011111111011111111011111111011111111011111111011111111011111111011111111011111111011111111011111111011111111011111111011111111011111111011 #
18
1:
0;
b0000010100000101000001010000010100000101000001010000010100000101000001010000010100000101000001010000010100000101000001010000010100000101000001010000010100000101000001010000010100000101000001010000010100000101000001010000010100000101000001010000010100000101 <
1J
#49
08
#50
b1111110110111111011011111101101111110110111111011011111101101111110110111111011011111101101111110110111111011011111101101111110110111111011011111101101111110110 ,
18
0:
0J
b00001 K
#51
08
#52
b1111110110011111101100111111011001111110110011111101100111111011001111110110011111101100 1
18
b00010 K
#53
08
#54
b111111011000111111011000111111011000111111011000 4
18
b00100 K
#55
08
#56
b11111101100001111110110000 6
18
b01000 K
#57
08
#58
b11111101100000 7
18
1F
b11111111111111111111111101100000 G
b10000 K
#59
08
#60
18
0F
b00000 K
#61
08
#62
18
#63
08
#64
18
#65
08
#66
18
#67
08
#68
18
#69
08
#70
b111111111111111111111111111111111111111111111111111111111111111111111111111111111111111111111111111111111111111111111111111111111111111111111111111111111111111111111111111111111111111111111111111111111111111111111111111111111111111111111111111111111111111111111111111111111111111111111111 #
18
1:
b0000000100000001000000010000000100000001000000010000000100000001000000010000000100000001000000010000000100000001000000010000000100000001000000010000000100000001000000010000000100000001000000010000000100000001000000010000000100000001000000010000000100000001 <
1J
#71
08
#72
b111111110111111110111111110111111110111111110111111110111111110111111110111111110111111110111111110111111110111111110111111110111111110111111110111111110111111110111111110111111110111111110111111110111111110111111110111111110111111110111111110111111110111111110111111110111111110111111110 #
b1111111110111111111011111111101111111110111111111011111111101111111110111111111011111111101111111110111111111011111111101111111110111111111011111111101111111110 ,
18
b0000001000000010000000100000001000000010000000100000001000000010000000100000001000000010000000100000001000000010000000100000001000000010000000100000001000000010000000100000001000000010000000100000001000000010000000100000001000000010000000100000001000000010 <
b00001 K
#73
08
#74
b111111101111111101111111101111111101111111101111111101111111101111111101111111101111111101111111101111111101111111101111111101111111101111111101111111101111111101111111101111111101111111101111111101111111101111111101111111101111111101111111101111111101111111101111111101111111101111111101 #
b1111111100111111110011111111001111111100111111110011111111001111111100111111110011111111001111111100111111110011111111001111111100111111110011111111001111111100 ,
b1111111110011111111100111111111001111111110011111111100111111111001111111110011111111100 1
18
b0000001100000011000000110000001100000011000000110000001100000011000000110000001100000011000000110000001100000011000000110000001100000011000000110000001100000011000000110000001100000011000000110000001100000011000000110000001100000011000000110000001100000011 <
b00011 K
#75
08
#76
b1111111010111111101011111110101111111010111111101011111110101111111010111111101011111110101111111010111111101011111110101111111010111111101011111110101111111010 ,
b1111111100011111111000111111110001111111100011111111000111111110001111111100011111111000 1
b111111111000111111111000111111111000111111111000 4
18
0:
0J
b00111 K
#77
08
#78
b1111111010011111110100111111101001111111010011111110100111111101001111111010011111110100 1
b111111110000111111110000111111110000111111110000 4
b11111111100001111111110000 6
18
b01110 K
#79
08
#80
b111111101000111111101000111111101000111111101000 4
b11111111000001111111100000 6
b11111111100000 7
18
1F
b11111111111111111111111111100000 G
b11100 K
#81
08
#82
b11111110100001111111010000 6
b11111111000000 7
18
b11111111111111111111111111000000 G
b11000 K
#83
08
#84
b11111110100000 7
18
b11111111111111111111111110100000 G
b10000 K
#85
08
#86
18
0F
b00000 K
#87
08
#88
18
#89
08
#90
18
#91
08
#92
18
1;
b0101010101010101000000000000000010101010101010101010101010101010 D
b0101010101010101000000000000000010101010101010101010101010101010 H
#93
08
#94
b000000000000000000000000000000000000000000000000000000000000000000000000111110110111110110111110110111110110111110110111110110111110110111110110000001010000001010000001010000001010000001010000001010000001010000001010000001010000001010000001010000001010000001010000001010000001010000001010 #
18
1:
0;
b0000101000001010000010100000101000001010000010100000101000001010000010100000101000001010000010100000101000001010000010100000101000001010000010100000101000001010000010100000101000001010000010100000101000001010000010100000101000001010000010100000101000001010 <
1J
#95
08
#96
b0000000000000000000000000000000000000000111110110011111011001111101100111110110000000101000000010100000001010000000101000000010100000001010000000101000000010100 ,
18
0:
0J
b00001 K
#97
08
#98
b0000000000000000000000111110110001111101100000000101000000001010000000010100000000101000 1
18
b00010 K
#99
08
#100
b000000000000111110110000000001010000000001010000 4
18
b00100 K
#101
08
#102
b11111101100000000010100000 6
18
b01000 K
#103
08
#104
b00000001010000 7
18
1F
b00000000000000000000000001010000 G
b10000 K
#105
08
#106
18
0F
b00000 K
