TDPU/vec_multi_core.sv
`timescale 1ns / 1ps
`include "package_def.sv"  //引入包定义文件
import package_def::*;
//在一个时间周期内并行计算默认参数为16对数据的TDPU核心
//该核心先进行权重锁存，然后以脉动形式输出结果
//logic [数量-1 : 0] [位宽-1 : 0] 变量名;
module vec_multi_core #(
    parameter int LEN = 16,  //并行度
    parameter int DATA_WIDTH = 8
) (

    input logic clk,
    input logic rst_n,  //异步复位
    input logic i_data_valid,  //输入数据有效信号（同步）
    input logic i_load_weight,  //加载权重信号（同步）
    input logic signed [LEN-1:0][DATA_WIDTH-1:0] i_data,  //输入激活值数组
    input weight_t [LEN-1:0] i_weight,  //输入权重数组
    output logic o_data_ready,  //输出结果有效信号（同步）
    output logic signed [31:0] o_result  //输出累加结果，选择32位以防溢出
);

  //0.权重寄存器(收到加载信号时锁存权重)
  weight_t [LEN-1:0] weight_reg;
  always_ff @(posedge clk or negedge rst_n) begin : core
    if (!rst_n) begin
      weight_reg <= '{default: W_ZERO};
    end else begin
      if (i_load_weight) begin
        weight_reg <= i_weight;//如果没有收到权重加载信号则保持原来的数据不变
      end
    end

  end

  //1.PE计算层
  //中间信号：用于处理符号扩展
  logic signed [LEN-1:0][31:0] product;
  logic product_ready;
  //计算每个激活值和权重点积的结果（并行生成）
  //根据权重值决定是加、减 还是 不变
  generate
    for (genvar i = 0; i < LEN; i++) begin : gen_PE  // genvar是生成循环专用变量
      always_ff @(posedge clk or negedge rst_n) begin
        if (!rst_n) begin
          product[i] <= 32'sd0;  // 每个元素独立复位
          product_ready <= 1'b0;
        end else begin
          if (i_data_valid) begin
            unique case (weight_reg[i])
              W_POS: begin
                product[i] <= 32'(i_data[i]);  // 符号扩展到32位
              end
              W_NEG: begin
                product[i] <= -32'(i_data[i]);  // 符号扩展并取负
              end
              W_ZERO: begin
                product[i] <= 32'sd0;
              end
              default: product[i] <= 32'sd0;
            endcase
          end else begin
            // 补充i_data_valid为低时的赋值，避免锁存器
            product[i] <= product[i];  // 保持原值（显式写，消除警告）

          end
          product_ready <= i_data_valid;
        end
      end
    end
  endgenerate


  //2. 参数化加法树
  // 计算加法树的层数: $clog2(LEN)
  localparam int TREE_DEPTH = $clog2(LEN);

  // 定义加法树的中间信号
  // tree_data[level][index]
  // 第0层是 product 结果 (LEN个)
  // 第1层是 LEN/2 个结果
  // ...
  // 第TREE_DEPTH层是 1 个结果
  logic signed [31:0] tree_data[TREE_DEPTH:0][LEN-1:0];//之所以定死LEN-1，是因为综合工具会自动省去不必要的寄存器
  logic [TREE_DEPTH:0] tree_valid;

  // 将PE层的输出连接到加法树第0层
  always_comb begin
    for (int i = 0; i < LEN; i++) begin
      tree_data[0][i] = product[i];
    end
    tree_valid[0] = product_ready;
  end

  // 生成加法树流水线
  generate
    for (genvar level = 0; level < TREE_DEPTH; level++) begin : gen_tree_level
      // 当前层节点数
      localparam int NUM_NODES = LEN >> (level + 1);

      for (genvar k = 0; k < NUM_NODES; k++) begin : gen_adder
        always_ff @(posedge clk or negedge rst_n) begin
          if (!rst_n) begin
            tree_data[level+1][k] <= 32'sd0;
          end else begin
            if (tree_valid[level]) begin
              // 相邻两个节点相加
              tree_data[level+1][k] <= tree_data[level][2*k] + tree_data[level][2*k+1];
            end
          end
        end
      end

      // Valid信号流水线传递
      always_ff @(posedge clk or negedge rst_n) begin
        if (!rst_n) begin
          tree_valid[level+1] <= 1'b0;
        end else begin
          tree_valid[level+1] <= tree_valid[level];
        end
      end
    end
  endgenerate

  //3. 输出处理
  // 最终结果在 tree_data[TREE_DEPTH][0]
  assign o_result = tree_data[TREE_DEPTH][0];
  assign o_data_ready = tree_valid[TREE_DEPTH];


endmodule

TDPU/waveform.vcd
$version Generated by VerilatedVcd $end
$timescale 1ps $end
 $scope module TOP $end
  $var wire 1 6 clk $end
  $var wire 1 7 rst_n $end
  $var wire 1 8 i_data_valid $end
  $var wire 1 9 i_load_weight $end
  $var wire 128 : i_data [127:0] $end
  $var wire 32 > i_weight [31:0] $end
  $var wire 1 ? o_data_ready $end
  $var wire 32 @ o_result [31:0] $end
  $scope module vec_multi_core $end
   $var wire 32 A LEN [31:0] $end
   $var wire 32 B DATA_WIDTH [31:0] $end
   $var wire 1 6 clk $end
   $var wire 1 7 rst_n $end
   $var wire 1 8 i_data_valid $end
   $var wire 1 9 i_load_weight $end
   $var wire 128 : i_data [127:0] $end
   $var wire 32 > i_weight [31:0] $end
   $var wire 1 ? o_data_ready $end
   $var wire 32 @ o_result [31:0] $end
   $var wire 32 # weight_reg [31:0] $end
   $var wire 512 $ product [511:0] $end
   $var wire 1 4 product_ready $end
   $var wire 32 C TREE_DEPTH [31:0] $end
   $var wire 5 5 tree_valid [4:0] $end
   $scope module gen_tree_level[0] $end
    $var wire 32 B NUM_NODES [31:0] $end
   $upscope $end
   $scope module gen_tree_level[1] $end
    $var wire 32 C NUM_NODES [31:0] $end
   $upscope $end
   $scope module gen_tree_level[2] $end
    $var wire 32 D NUM_NODES [31:0] $end
   $upscope $end
   $scope module gen_tree_level[3] $end
    $var wire 32 E NUM_NODES [31:0] $end
   $upscope $end
   $scope module unnamedblk1 $end
    $var wire 32 F i [31:0] $end
   $upscope $end
  $upscope $end
 $upscope $end
$enddefinitions $end


#0
b00000000000000000000000000000000 #
b00000000000000000000000000000000000000000000000000000000000000000000000000000000000000000000000000000000000000000000000000000000000000000000000000000000000000000000000000000000000000000000000000000000000000000000000000000000000000000000000000000000000000000000000000000000000000000000000000000000000000000000000000000000000000000000000000000000000000000000000000000000000000000000000000000000000000000000000000000000000000000000000000000000000000000000000000000000000000000000000000000000000000000000000000000000 $
04
b00000 5
16
07
08
09
b00000000000000000000000000000000000000000000000000000000000000000000000000000000000000000000000000000000000000000000000000000000 :
b01010101010101010101010101010101 >
0?
b00000000000000000000000000000000 @
b00000000000000000000000000010000 A
b00000000000000000000000000001000 B
b00000000000000000000000000000100 C
b00000000000000000000000000000010 D
b00000000000000000000000000000001 E
b00000000000000000000000000010000 F
#1
06
#2
b01010101010101010101010101010101 #
16
#3
06
#4
16
#5
06
#6
16
#7
06
#8
16
#9
06
#10
16
#11
06
#12
16
#13
06
#14
16
#15
06
#16
16
#17
06
#18
16
#19
06
#20
16
17
#21
06
#22
b10101010101010101010101010101010 #
16
19
b10101010101010101010101010101010 >
#23
06
#24
b00000000000000000000000000001010000000000000000000000000000010100000000000000000000000000000101000000000000000000000000000001010000000000000000000000000000010100000000000000000000000000000101000000000000000000000000000001010000000000000000000000000000010100000000000000000000000000000101000000000000000000000000000001010000000000000000000000000000010100000000000000000000000000000101000000000000000000000000000001010000000000000000000000000000010100000000000000000000000000000101000000000000000000000000000001010 $
14
b00001 5
16
18
09
b00001010000010100000101000001010000010100000101000001010000010100000101000001010000010100000101000001010000010100000101000001010 :
#25
06
#26
04
b00010 5
16
08
#27
06
#28
b00100 5
16
#29
06
#30
b01000 5
16
#31
06
#32
b10000 5
16
1?
b00000000000000000000000010100000 @
#33
06
#34
b00000 5
16
0?
#35
06
#36
16
#37
06
#38
16
#39
06
#40
16
#41
06
#42
16
#43
06
#44
16
#45
06
#46
b00000000000000000000000000000000 #
16
19
b00000000000000000000000000000000 >
#47
06
#48
b11111111111111111111111111111011111111111111111111111111111110111111111111111111111111111111101111111111111111111111111111111011111111111111111111111111111110111111111111111111111111111111101111111111111111111111111111111011111111111111111111111111111110111111111111111111111111111111101111111111111111111111111111111011111111111111111111111111111110111111111111111111111111111111101111111111111111111111111111111011111111111111111111111111111110111111111111111111111111111111101111111111111111111111111111111011 $
14
b00001 5
16
18
09
b00000101000001010000010100000101000001010000010100000101000001010000010100000101000001010000010100000101000001010000010100000101 :
#49
06
#50
04
b00010 5
16
08
#51
06
#52
b00100 5
16
#53
06
#54
b01000 5
16
#55
06
#56
b10000 5
16
1?
b11111111111111111111111110110000 @
#57
06
#58
b00000 5
16
0?
#59
06
#60
16
#61
06
#62
16
#63
06
#64
16
#65
06
#66
16
#67
06
#68
16
#69
06
#70
b11111111111111111111111111111111111111111111111111111111111111111111111111111111111111111111111111111111111111111111111111111111111111111111111111111111111111111111111111111111111111111111111111111111111111111111111111111111111111111111111111111111111111111111111111111111111111111111111111111111111111111111111111111111111111111111111111111111111111111111111111111111111111111111111111111111111111111111111111111111111111111111111111111111111111111111111111111111111111111111111111111111111111111111111111111111 $
14
b00001 5
16
18
b00000001000000010000000100000001000000010000000100000001000000010000000100000001000000010000000100000001000000010000000100000001 :
#71
06
#72
b11111111111111111111111111111110111111111111111111111111111111101111111111111111111111111111111011111111111111111111111111111110111111111111111111111111111111101111111111111111111111111111111011111111111111111111111111111110111111111111111111111111111111101111111111111111111111111111111011111111111111111111111111111110111111111111111111111111111111101111111111111111111111111111111011111111111111111111111111111110111111111111111111111111111111101111111111111111111111111111111011111111111111111111111111111110 $
b00011 5
16
b00000010000000100000001000000010000000100000001000000010000000100000001000000010000000100000001000000010000000100000001000000010 :
#73
06
#74
b11111111111111111111111111111101111111111111111111111111111111011111111111111111111111111111110111111111111111111111111111111101111111111111111111111111111111011111111111111111111111111111110111111111111111111111111111111101111111111111111111111111111111011111111111111111111111111111110111111111111111111111111111111101111111111111111111111111111111011111111111111111111111111111110111111111111111111111111111111101111111111111111111111111111111011111111111111111111111111111110111111111111111111111111111111101 $
b00111 5
16
b00000011000000110000001100000011000000110000001100000011000000110000001100000011000000110000001100000011000000110000001100000011 :
#75
06
#76
04
b01110 5
16
08
#77
06
#78
b11100 5
16
1?
b11111111111111111111111111110000 @
#79
06
#80
b11000 5
16
b11111111111111111111111111100000 @
#81
06
#82
b10000 5
16
b11111111111111111111111111010000 @
#83
06
#84
b00000 5
16
0?
